ARM_PC/DataMemory.v
`timescale 1ns / 1ps

`define SIZE 1024

module DataMemory(ReadData , Address , WriteData , MemoryRead , MemoryWrite , Clock);
    input [63:0]      WriteData;
    input [63:0]      Address;
    input             Clock, MemoryRead, MemoryWrite;
    output reg [63:0] ReadData;

    reg [7:0]         memBank [`SIZE-1:0];


    // This task is used to write arbitrary data to the Data Memory by
    // the intialization block.
    task initset;
      input [63:0] addr;
      input [63:0] data;
      begin
     memBank[addr] =  data[63:56] ; // Big-endian for the win...
     memBank[addr+1] =  data[55:48];
     memBank[addr+2] =  data[47:40];
     memBank[addr+3] =  data[39:32];
     memBank[addr+4] =  data[31:24];
     memBank[addr+5] =  data[23:16];
     memBank[addr+6] =  data[15:8];
     memBank[addr+7] =  data[7:0];
      end
    endtask


    initial
    begin
        // preseting some data in the data memory used by test #1

        // Address 0x0 gets 0x1
        initset( 64'h0,  64'h1);  //Counter variable
        initset( 64'h8,  64'ha);  //Part of mask
        initset( 64'h10, 64'h5);  //Other part of mask
        initset( 64'h18, 64'h0ffbea7deadbeeff); //big constant
        initset( 64'h20, 64'h0); //clearing space

        // Add any data you need for your tests here.

    end

    // This always block reads the data memory and places a double word
    // on the ReadData bus.
    always @(posedge Clock)
    begin
        if(MemoryRead)
        begin
            ReadData[63:56] <= #20 memBank[Address];
            ReadData[55:48] <= #20 memBank[Address+1];
            ReadData[47:40] <= #20 memBank[Address+2];
            ReadData[39:32] <= #20 memBank[Address+3];
            ReadData[31:24] <= #20 memBank[Address+4];
            ReadData[23:16] <= #20 memBank[Address+5];
            ReadData[15:8] <= #20 memBank[Address+6];
            ReadData[7:0] <= #20 memBank[Address+7];

            $display("Reading Address:%h Data:%h",Address, ReadData);
        end
    end

    // This always block takes data from the WriteData bus and writes
    // it into the DataMemory.
    always @(posedge Clock)
    begin
        if(MemoryWrite)
        begin
            memBank[Address] <= #20 WriteData[63:56] ;
            memBank[Address+1] <= #20 WriteData[55:48];
            memBank[Address+2] <= #20 WriteData[47:40];
            memBank[Address+3] <= #20 WriteData[39:32];
            memBank[Address+4] <= #20 WriteData[31:24];
            memBank[Address+5] <= #20 WriteData[23:16];
            memBank[Address+6] <= #20 WriteData[15:8];
            memBank[Address+7] <= #20 WriteData[7:0];
            // Could be useful for debugging:
            $display("Writing Address:%h Data:%h",Address, WriteData);
        end
    end
endmodule

ARM_PC/ALU.v
`define AND   4'b0000
`define OR    4'b0001
`define ADD   4'b0010
`define SUB   4'b0110
`define PassB 4'b0111
`define MOVZ  4'b11??

module ALU(BusW, BusA, BusB, ALUCtrl, Zero);

    parameter n = 64;

    //declaring ports
    output  [n-1:0] BusW;
    input   [n-1:0] BusA, BusB;
    input   [3:0] ALUCtrl;
    output  reg Zero;

    //internal variables
    reg     [n-1:0] BusW;

    //continuous block assignment
    always @(ALUCtrl or BusA or BusB or BusW) begin     //always run assignment if these values change

        casez (ALUCtrl)     //ALU opcode

            `AND: begin
                BusW <= #20 BusA & BusB;
                //$display("AND BusA: %h BusB: %h BusW: %h", BusA, BusB, BusW);
            end

            `OR: begin
                BusW <= #20 BusA | BusB;
                //$display("OR BusA: %h BusB: %h BusW: %h", BusA, BusB, BusW);
            end

            `ADD: begin
                BusW <= #20 BusA + BusB;
                //$display("ADD BusA: %h BusB: %h BusW: %h", BusA, BusB, BusW);
            end

            `SUB: begin
                BusW <= #20 BusA - BusB;
                //$display("SUB BusA: %h BusB: %h BusW: %h", BusA, BusB, BusW);
            end

            `PassB: begin
                BusW <= #20 BusB;
                //$display("PASSB BusA: %h BusB: %h BusW: %h", BusA, BusB, BusW);
            end

            `MOVZ:  begin
                BusW <= #20 BusB << (ALUCtrl[1:0]*16);
                //$display("MOVZ BusA: %h BusB: %h BusW: %h", BusA, BusB, BusW);
            end

        endcase

        Zero <= (BusW == 64'b0);
        //$display("Zero: %h BusW: %h", Zero, BusW);
    end
endmodule

ARM_PC/SignExtender.v
module SignExtender(BusImm, Imm26, Ctrl);

  //declaring ports
  output [63:0] BusImm;
  input [25:0] Imm26;
  input [2:0] Ctrl;

  //internal variables
  reg [63:0] BusImm;

  always @(*)   begin

        case (Ctrl)
        //I-type
        3'b000:    BusImm <= {{52{1'b0}}, Imm26[21:10]};

        //D-type
        3'b001:    BusImm <= {{55{Imm26[20]}}, Imm26[20:12]};

        //B-type
        3'b010:    BusImm <= {{38{Imm26[25]}}, Imm26[25:0]};

        //CB-type
        3'b011:    BusImm <= {{45{Imm26[23]}}, Imm26[23:5]};

        //IW-type (used for MOVZ)
        3'b100:     BusImm <= {{48{1'b0}}, Imm26[20:5]};
        endcase
    end
endmodule

ARM_PC/NextPClogic.v
module NextPClogic(NextPC, CurrentPC, SignExtImm64, Branch, ALUZero, Uncondbranch);

    //declaring ports
    input [63:0] CurrentPC, SignExtImm64;
    input Branch, ALUZero, Uncondbranch;
    output reg [63:0] NextPC;

    //internal variable
    reg mux;

    always @(*)
        begin

            //mutiplexers have delay of #1
            //mux gate logic for PC addressing
            mux <= #1 Uncondbranch | (Branch & ALUZero);

            if(mux)
                begin
                    //ADD has delay of #2
                    NextPC <= #2 CurrentPC + (SignExtImm64 << 2);
                end

            else if(~mux)
                begin
                    //ADDI has delay of #1
                    NextPC <= #1 CurrentPC + 4;
                end
        end
endmodule

ARM_PC/RegisterFile.v
module RegisterFile(BusA, BusB, BusW, RW, RA, RB, RegWr, Clk);
    output [63:0] BusA;
    output [63:0] BusB;
    input [63:0] BusW;
    input [4:0] RW, RA, RB;
    input RegWr;
    input Clk;

    //vector of 32 registers
    reg [63:0] registers [31:0];

    assign #2 BusA = registers[RA];     //BusA = register at RA
    assign #2 BusB = registers[RB];     //BusB = register at RB

    initial
        begin
            registers[31] <= 64'b0;     //sets register[31] = 64'h0
        end

    always @ (negedge Clk)
        begin
            if(RegWr & RW != 5'b11111)
                begin    //If Registr Write = 1 and is not register[31]
                    registers[RW] <= #3 BusW;   //Write input to Register at RW
                end
        end
endmodule

ARM_PC/SingleCycleControl.v
`define OPCODE_ANDREG 11'b?0001010???
`define OPCODE_ORRREG 11'b?0101010???
`define OPCODE_ADDREG 11'b?0?01011???
`define OPCODE_SUBREG 11'b?1?01011???

`define OPCODE_ADDIMM 11'b?0?10001???
`define OPCODE_SUBIMM 11'b?1?10001???

`define OPCODE_MOVZ   11'b110100101??

`define OPCODE_B      11'b?00101?????
`define OPCODE_CBZ    11'b?011010????

`define OPCODE_LDUR   11'b??111000010
`define OPCODE_STUR   11'b??111000000


module control(
    output reg reg2loc,
    output reg alusrc,
    output reg mem2reg,
    output reg regwrite,
    output reg memread,
    output reg memwrite,
    output reg branch,
    output reg uncond_branch,
    output reg [3:0] aluop,
    output reg [2:0] signop,
    input [10:0] opcode
);


always @(*)
begin

    casez (opcode)

        /* Add cases here for each instruction your processor supports */
        `OPCODE_ANDREG:     //AND opcode
          begin
              reg2loc       <= 1'b0;      //AND control signals
              alusrc        <= 1'b0;
              mem2reg       <= 1'b0;
              regwrite      <= 1'b1;
              memread       <= 1'b0;
              memwrite      <= 1'b0;
              branch        <= 1'b0;
              uncond_branch <= 1'b0;
              aluop         <= 4'b0000;
              signop        <= 3'bxxx;
          end

        `OPCODE_ORRREG:     //ORR opcode
        begin
              reg2loc       <= 1'b0;    //ORR control signals
              alusrc        <= 1'b0;
              mem2reg       <= 1'b0;
              regwrite      <= 1'b1;
              memread       <= 1'b0;
              memwrite      <= 1'b0;
              branch        <= 1'b0;
              uncond_branch <= 1'b0;
              aluop         <= 4'b0001;
              signop        <= 3'bxxx;
        end

        `OPCODE_ADDREG:     //ADD opcode
        begin
              reg2loc       <= 1'b0;    //ADD control signals
              alusrc        <= 1'b0;
              mem2reg       <= 1'b0;
              regwrite      <= 1'b1;
              memread       <= 1'b0;
              memwrite      <= 1'b0;
              branch        <= 1'b0;
              uncond_branch <= 1'b0;
              aluop         <= 4'b0010;
              signop        <= 3'bxxx;
        end

        `OPCODE_SUBREG:     //SUB opcode
        begin
              reg2loc       <= 1'b0;    //SUB control signals
              alusrc        <= 1'b0;
              mem2reg       <= 1'b0;
              regwrite      <= 1'b1;
              memread       <= 1'b0;
              memwrite      <= 1'b0;
              branch        <= 1'b0;
              uncond_branch <= 1'b0;
              aluop         <= 4'b0110;
              signop        <= 3'bxxx;
        end

        `OPCODE_ADDIMM:     //ADDI opcode
        begin
            reg2loc       <= 1'b0;     //ADDI control signals
            alusrc        <= 1'b1;
            mem2reg       <= 1'b0;
            regwrite      <= 1'b1;
            memread       <= 1'b0;
            memwrite      <= 1'b0;
            branch        <= 1'b0;
            uncond_branch <= 1'b0;
            aluop         <= 4'b0010;
            signop        <= 3'b000;
        end

        `OPCODE_SUBIMM:     //SUBI opcode
        begin
            reg2loc       <= 1'b1;      //SUBI control signals
            alusrc        <= 1'b0;
            mem2reg       <= 1'b0;
            regwrite      <= 1'b1;
            memread       <= 1'b0;
            memwrite      <= 1'b0;
            branch        <= 1'b0;
            uncond_branch <= 1'b0;
            aluop         <= 4'b0110;
            signop        <= 3'b000;
        end


        `OPCODE_MOVZ:       //MOVZ opcode
        begin
            reg2loc       <= 1'b1;      //MOVZ control signals
            alusrc        <= 1'b1;
            mem2reg       <= 1'b0;
            regwrite      <= 1'b1;
            memread       <= 1'b0;
            memwrite      <= 1'b0;
            branch        <= 1'b0;
            uncond_branch <= 1'b0;
            aluop         <= {{2'b11},{opcode[1:0]}};   //last two opcode bits used in ALU
            signop        <= 3'b100;                    //send to alu through aluop
        end


        `OPCODE_B:          //B opcode
        begin
            reg2loc       <= 1'bx;      //Branch control signals
            alusrc        <= 1'b1;
            mem2reg       <= 1'bx;
            regwrite      <= 1'b0;
            memread       <= 1'b0;
            memwrite      <= 1'b0;
            branch        <= 1'b0;
            uncond_branch <= 1'b1;
            aluop         <= 4'b0111;
            signop        <= 3'b010;
        end

        `OPCODE_CBZ:        //CBZ opcode
        begin
            reg2loc       <= 1'b1;      //CBZ control signals
            alusrc        <= 1'b0;
            mem2reg       <= 1'bx;
            regwrite      <= 1'b0;
            memread       <= 1'b0;
            memwrite      <= 1'b0;
            branch        <= 1'b1;
            uncond_branch <= 1'b0;
            aluop         <= 4'b0111;
            signop        <= 3'b011;
        end

        `OPCODE_LDUR:       //LDUR opcode
        begin
            reg2loc       <= 1'bx;      //LDUR control signals
            alusrc        <= 1'b1;
            mem2reg       <= 1'b1;
            regwrite      <= 1'b1;
            memread       <= 1'b1;
            memwrite      <= 1'b0;
            branch        <= 1'b0;
            uncond_branch <= 1'b0;
            aluop         <= 4'b0010;
            signop        <= 3'b001;
        end

        `OPCODE_STUR:       //STUR opcode
        begin
            reg2loc       <= 1'b1;      //STUR control signals
            alusrc        <= 1'b1;
            mem2reg       <= 1'bx;
            regwrite      <= 1'b0;
            memread       <= 1'b0;
            memwrite      <= 1'b1;
            branch        <= 1'b0;
            uncond_branch <= 1'b0;
            aluop         <= 4'b0010;
            signop        <= 3'b001;
        end

        default:        //default case and control signals
        begin
            reg2loc       <= 1'bx;
            alusrc        <= 1'bx;
            mem2reg       <= 1'bx;
            regwrite      <= 1'b0;
            memread       <= 1'b0;
            memwrite      <= 1'b0;
            branch        <= 1'b0;
            uncond_branch <= 1'b0;
            aluop         <= 4'bxxxx;
            signop        <= 3'bxxx;
        end
    endcase
end

endmodule

ARM_PC/InstructionMemory.v
`timescale 1ns / 1ps
/*
 * Module: InstructionMemory
 *
 * Implements read-only instruction memory
 *
 */
module InstructionMemory(Data, Address);
   parameter T_rd = 20;
   parameter MemSize = 40;

   output [31:0] Data;
   input [63:0]  Address;
   reg [31:0] 	 Data;

   /*
    * ECEN 350 Processor Test Functions
    * Texas A&M University
    */

   always @ (Address) begin
      case(Address)

	/* Test Program 1:
	 * Program loads constants from the data memory. Uses these constants to test
	 * the following instructions: LDUR, ORR, AND, CBZ, ADD, SUB, STUR and B.
	 *
	 * Assembly code for test:
	 *
	 * 0: LDUR X9, [XZR, 0x0]    //Load 1 into x9
	 * 4: LDUR X10, [XZR, 0x8]   //Load a into x10
	 * 8: LDUR X11, [XZR, 0x10]  //Load 5 into x11
	 * C: LDUR X12, [XZR, 0x18]  //Load big constant into x12
	 * 10: LDUR X13, [XZR, 0x20]  //load a 0 into X13
	 *
	 * 14: ORR X10, X10, X11  //Create mask of 0xf
	 * 18: AND X12, X12, X10  //Mask off low order bits of big constant
	 *
	 * loop:
	 * 1C: CBZ X12, end  //while X12 is not 0
	 * 20: ADD X13, X13, X9  //Increment counter in X13
	 * 24: SUB X12, X12, X9  //Decrement remainder of big constant in X12
	 * 28: B loop  //Repeat till X12 is 0
	 * 2C: STUR X13, [XZR, 0x20]  //store back the counter value into the memory location 0x20
	 */

	63'h000: Data = 32'hF84003E9;
	63'h004: Data = 32'hF84083EA;
	63'h008: Data = 32'hF84103EB;
	63'h00c: Data = 32'hF84183EC;
	63'h010: Data = 32'hF84203ED;
	63'h014: Data = 32'hAA0B014A;
	63'h018: Data = 32'h8A0A018C;
	63'h01c: Data = 32'hB400008C;
	63'h020: Data = 32'h8B0901AD;
	63'h024: Data = 32'hCB09018C;
	63'h028: Data = 32'h17FFFFFD;
	63'h02c: Data = 32'hF80203ED;
	63'h030: Data = 32'hF84203ED;  //One last load to place stored value on memdbus for test checking.


    63'h038: Data = 32'b11010010100000000000000000001001;      //MOVZ X9, 0x0 {LSL, #0}
	63'h03c: Data = 32'b11010010111000100100011010001000;      //MOVZ X8, 0x1234 {LSL, #3}
	63'h040: Data = 32'b10101010000010000000000100101001;      //ORR  X9, X9, X8
	63'h044: Data = 32'b11010010110010101100111100001000;      //MOVZ X8, 0x5678 {LSL, #2}
	63'h048: Data = 32'b10101010000010000000000100101001;      //ORR  X9, X9, X8
	63'h04c: Data = 32'b11010010101100110101011110001000;      //MOVZ X8, 0x9abc {LSL, #1}
	63'h050: Data = 32'b10101010000010000000000100101001;      //ORR  X9, X9, X8
	63'h054: Data = 32'b11010010100110111101111000001000;      //MOVZ X8, 0xdef0 {LSL, #0}
	63'h058: Data = 32'b10101010000010000000000100101001;      //ORR  X9, X9, X8
	63'h05c: Data = 32'b11010010100000000000010100001000;      //MOVZ X8, 0x28 {LSL, #0}
    63'h060: Data = 32'b11111000000000000000000100001001;      //STUR X9, [X8, 0x0]
    63'h064: Data = 32'b11111000010000101000001111101010;      //LDUR X10,[X9, 0x0]

	default: Data = 32'hXXXXXXXX;
      endcase
   end
endmodule

ARM_PC/SingleCycleProc.v
module singlecycle(
    input CLK,
    input resetl,
    input [63:0] startpc,
    output reg [63:0] currentpc,
    output [63:0] dmemout
);
    // Next PC connections
    wire [63:0] nextpc;       // The next PC, to be updated on clock cycle

    // Instruction Memory connections
    wire [31:0] instruction;  // The current instruction

    // Parts of instruction
    wire [4:0] rd;            // The destination register
    wire [4:0] rm;            // Operand 1
    wire [4:0] rn;            // Operand 2
    wire [10:0] opcode;

//---------------------------------------------------------------------------------
    wire [15:0] moveimm;
//--------------------------------------------------------------------------------


    // Control wires
    wire reg2loc;
    wire alusrc;
    wire mem2reg;
    wire regwrite;
    wire memread;
    wire memwrite;
    wire branch;
    wire uncond_branch;
    wire [3:0] aluctrl;
    wire [2:0] signop;

    // Register file connections
    wire [63:0] regoutA;     // Output A
    wire [63:0] regoutB;     // Output B

    // ALU connections
    wire [63:0] aluout;
    wire zero;

    // Sign Extender connections
    wire [25:0] inext;
    wire [63:0] extimm;

    // PC update logic
    always @(negedge CLK)
    begin
        if (resetl)
            currentpc <= nextpc;
        else
            currentpc <= startpc;
    end

    // Parts of instruction
    assign rd = instruction[4:0];
    assign rm = instruction[9:5];
    assign rn = reg2loc ? instruction[4:0] : instruction[20:16];
    assign opcode = instruction[31:21];
    assign inext = instruction[25:0];       //sign extender input

    InstructionMemory imem (
        .Data(instruction),
        .Address(currentpc)
    );

    control control (
        .reg2loc(reg2loc),
        .alusrc(alusrc),
        .mem2reg(mem2reg),
        .regwrite(regwrite),
        .memread(memread),
        .memwrite(memwrite),
        .branch(branch),
        .uncond_branch(uncond_branch),
        .aluop(aluctrl),
        .signop(signop),
        .opcode(opcode)
    );

    /*
    * Connect the remaining datapath elements below.
    * Do not forget any additional multiplexers that may be required.
    */

//------------------------------------------------------------------------
    //multiplexers
    wire [63:0] aluBin;
    wire [63:0] memMux;

    //mux for ALU BusB input
    assign aluBin = alusrc ? extimm : regoutB;

    //mux for Data Memory output
    assign memMux = mem2reg ? dmemout: aluout;

    //connecting register file
    RegisterFile Regfil (
          .BusA(regoutA),
          .BusB(regoutB),
          .BusW(memMux),
          .RW(rd),
          .RA(rm),
          .RB(rn),
          .RegWr(regwrite),
          .Clk(CLK)
    );

    //connecting pclogic
    NextPClogic pcLogic (
            .NextPC(nextpc),
            .CurrentPC(currentpc),
            .SignExtImm64(extimm),
            .Branch(branch),
            .ALUZero(zero),
            .Uncondbranch(uncond_branch)
    );

    //conecting sign extender
    SignExtender SignExt (
          .BusImm(extimm),
          .Imm26(inext),
          .Ctrl(signop)
    );

    //connecting ALU
    ALU ALU (
          .BusW(aluout),
          .BusA(regoutA),
          .BusB(aluBin),
          .ALUCtrl(aluctrl),
          .Zero(zero)
    );

    //connecting DataMemory
    DataMemory memory (
            .ReadData(dmemout),
            .Address(aluout),
            .WriteData(regoutB),
            .MemoryRead(memread),
            .MemoryWrite(memwrite),
            .Clock(CLK)
    );

endmodule

ARM_PC/SingleCycleProcTest.v
`timescale 1ns / 1ps

`define STRLEN 32
`define HalfClockPeriod 60
`define ClockPeriod `HalfClockPeriod * 2

`include "ALU.v"
`include "DataMemory.v"
`include "InstructionMemory.v"
`include "NextPClogic.v"
`include "RegisterFile.v"
`include "SignExtender.v"
`include "SingleCycleControl.v"
`include "SingleCycleProc.v"

module SingleCycleProcTest_v;

    initial
    begin
        $dumpfile("singlecycle.vcd");
        $dumpvars;
    end

    //tasks are used to check if a given test has passed and
    //confirm that all tests passed.
    task passTest;
        input [63:0] actualOut, expectedOut;
        input [`STRLEN*8:0] testType;
        inout [7:0] 	  passed;

        if(actualOut == expectedOut)
            begin
                $display ("%s passed", testType);
                passed = passed + 1;
            end

        else
            begin
                $display ("%s failed: 0x%x should be 0x%x", testType, actualOut, expectedOut);
            end
    endtask

    task allPassed;
        input [7:0] passed;
        input [7:0] numTests;

        if(passed == numTests) $display ("All tests passed");
        else $display("Some tests failed: %d of %d passed", passed, numTests);
    endtask

    // Inputs
    reg        CLK;
    reg        Reset_L;
    reg [63:0] startPC;
    reg [7:0]  passed;
    reg [15:0] watchdog;

    // Outputs
    wire [63:0] dMemOut;
    wire [63:0] currentPC;

    // Instantiate the Unit Under Test (UUT)
    singlecycle uut (
        .CLK(CLK),
        .resetl(Reset_L),
        .startpc(startPC),
        .currentpc(currentPC),
        .dmemout(dMemOut)
    );

    initial begin
        // Initialize Inputs
        Reset_L = 1;
        startPC = 0;
        passed = 0;

        // Initialize Watchdog timer
        watchdog = 0;

        // Wait for global reset
        #(1 * `ClockPeriod);

        // Program 1
        #1
        Reset_L = 0; startPC = 0;
        #(1 * `ClockPeriod);
        Reset_L = 1;

        // ***********************************************************
        // This while loop will continue cycling the processor until the
        // PC reaches the final instruction in the first test.  If the
        // program forms an infinite loop, never reaching the end, the
        // watchdog timer will kick in and kill simulation after 64K
        // cycles.
        // ***********************************************************

        while (currentPC < 64'h34)
            begin
                #(1 * `ClockPeriod);
                $display("CurrentPC:%h",currentPC);
            end
        //One more cycle to load the pass code from the DataMemory.
        #(1 * `ClockPeriod);
        passTest(dMemOut, 64'hF, "Results of Program 1", passed);

        // ***********************************************************
        while (currentPC < 64'h64)
        begin
           #(1 * `ClockPeriod);
           $display("CurrentPC:%h",currentPC);
        end

        // One more cycle to load the pass code from the DataMemory.
        #(1 * `ClockPeriod);
        passTest(dMemOut, 64'h123456789abcdef0, "Results of Program 2", passed);
        // ***********************************************************

        // Done
        allPassed(passed, 2);
        $finish;
    end

    initial begin
        CLK = 0;
    end

    // The following is correct if clock starts at LOW level at StartTime //
    always begin
        #`HalfClockPeriod CLK = ~CLK;
        #`HalfClockPeriod CLK = ~CLK;
        watchdog = watchdog +1;
    end

    // Kill the simulation if the watchdog hits 64K cycles
    always @*
        if (watchdog == 16'hFF)
        begin
            $display("Watchdog Timer Expired.");
            $finish;
        end
endmodule

ARM_PC/singlecycle.vcd
$date
	Wed Oct 23 22:54:23 2019
$end
$version
	Icarus Verilog
$end
$timescale
	1ps
$end
$scope module SingleCycleProcTest_v $end
$var wire 64 ! dMemOut [63:0] $end
$var wire 64 " currentPC [63:0] $end
$var reg 1 # CLK $end
$var reg 1 $ Reset_L $end
$var reg 8 % passed [7:0] $end
$var reg 64 & startPC [63:0] $end
$var reg 16 ' watchdog [15:0] $end
$scope module uut $end
$var wire 1 # CLK $end
$var wire 1 $ resetl $end
$var wire 64 ( startpc [63:0] $end
$var wire 1 ) zero $end
$var wire 1 * uncond_branch $end
$var wire 3 + signop [2:0] $end
$var wire 5 , rn [4:0] $end
$var wire 5 - rm [4:0] $end
$var wire 1 . regwrite $end
$var wire 64 / regoutB [63:0] $end
$var wire 64 0 regoutA [63:0] $end
$var wire 1 1 reg2loc $end
$var wire 5 2 rd [4:0] $end
$var wire 11 3 opcode [10:0] $end
$var wire 64 4 nextpc [63:0] $end
$var wire 1 5 memwrite $end
$var wire 1 6 memread $end
$var wire 64 7 memMux [63:0] $end
$var wire 1 8 mem2reg $end
$var wire 32 9 instruction [31:0] $end
$var wire 26 : inext [25:0] $end
$var wire 64 ; extimm [63:0] $end
$var wire 64 < dmemout [63:0] $end
$var wire 1 = branch $end
$var wire 1 > alusrc $end
$var wire 64 ? aluout [63:0] $end
$var wire 4 @ aluctrl [3:0] $end
$var wire 64 A aluBin [63:0] $end
$var reg 64 B currentpc [63:0] $end
$scope module ALU $end
$var wire 64 C BusB [63:0] $end
$var wire 64 D BusA [63:0] $end
$var wire 4 E ALUCtrl [3:0] $end
$var reg 64 F BusW [63:0] $end
$var reg 1 ) Zero $end
$upscope $end
$scope module Regfil $end
$var wire 64 G BusA [63:0] $end
$var wire 64 H BusB [63:0] $end
$var wire 64 I BusW [63:0] $end
$var wire 1 # Clk $end
$var wire 5 J RA [4:0] $end
$var wire 5 K RB [4:0] $end
$var wire 5 L RW [4:0] $end
$var wire 1 . RegWr $end
$upscope $end
$scope module SignExt $end
$var wire 26 M Imm26 [25:0] $end
$var wire 3 N Ctrl [2:0] $end
$var reg 64 O BusImm [63:0] $end
$upscope $end
$scope module control $end
$var wire 11 P opcode [10:0] $end
$var reg 4 Q aluop [3:0] $end
$var reg 1 > alusrc $end
$var reg 1 = branch $end
$var reg 1 8 mem2reg $end
$var reg 1 6 memread $end
$var reg 1 5 memwrite $end
$var reg 1 1 reg2loc $end
$var reg 1 . regwrite $end
$var reg 3 R signop [2:0] $end
$var reg 1 * uncond_branch $end
$upscope $end
$scope module imem $end
$var wire 64 S Address [63:0] $end
$var reg 32 T Data [31:0] $end
$upscope $end
$scope module memory $end
$var wire 64 U Address [63:0] $end
$var wire 1 # Clock $end
$var wire 1 6 MemoryRead $end
$var wire 1 5 MemoryWrite $end
$var wire 64 V WriteData [63:0] $end
$var reg 64 W ReadData [63:0] $end
$scope task initset $end
$var reg 64 X addr [63:0] $end
$var reg 64 Y data [63:0] $end
$upscope $end
$upscope $end
$scope module pcLogic $end
$var wire 1 ) ALUZero $end
$var wire 1 = Branch $end
$var wire 64 Z CurrentPC [63:0] $end
$var wire 64 [ SignExtImm64 [63:0] $end
$var wire 1 * Uncondbranch $end
$var reg 64 \ NextPC [63:0] $end
$var reg 1 ] mux $end
$upscope $end
$upscope $end
$scope task allPassed $end
$var reg 8 ^ numTests [7:0] $end
$var reg 8 _ passed [7:0] $end
$upscope $end
$scope task passTest $end
$var reg 64 ` actualOut [63:0] $end
$var reg 64 a expectedOut [63:0] $end
$var reg 8 b passed [7:0] $end
$var reg 257 c testType [256:0] $end
$upscope $end
$upscope $end
$enddefinitions $end
#0
$dumpvars
bx c
bx b
bx a
bx `
bx _
bx ^
x]
bx \
bx [
bx Z
b0 Y
b100000 X
bx W
bx V
bx U
bx T
bx S
bx R
bx Q
bx P
bx O
bx N
bx M
bx L
bx K
bx J
bx I
bx H
bx G
bx F
bx E
bx D
bx C
bx B
bx A
bx @
bx ?
x>
x=
bx <
bx ;
bx :
bx 9
x8
bx 7
x6
x5
bx 4
bx 3
bx 2
x1
bx 0
bx /
x.
bx -
bx ,
bx +
x*
x)
b0 (
b0 '
b0 &
b0 %
1$
0#
bx "
bx !
$end
#60000
1#
#120000
b1 '
0#
#121000
0$
#180000
1#
#240000
b0 A
b0 C
b0 ;
b0 O
b0 [
b1 +
b1 N
b1 R
b10 @
b10 E
b10 Q
0*
0=
05
16
1.
18
1>
b0x00x ,
b0x00x K
b10000000000001111101001 :
b10000000000001111101001 M
b11111000010 3
b11111000010 P
b11111 -
b11111 J
b1001 2
b1001 L
b11111000010000000000001111101001 9
b11111000010000000000001111101001 T
b0 "
b0 B
b0 S
b0 Z
b10 '
0#
#241000
0]
1$
#242000
b100 4
b100 \
b0 0
b0 D
b0 G
#262000
1)
b0 ?
b0 F
b0 U
#300000
1#
#320000
b1 7
b1 I
b1 !
b1 <
b1 W
#360000
b1000 A
b1000 C
b1000 ;
b1000 O
b1000 [
b0x0x0 ,
b0x0x0 K
b10000001000001111101010 :
b10000001000001111101010 M
b1010 2
b1010 L
b11111000010000001000001111101010 9
b11111000010000001000001111101010 T
b100 "
b100 B
b100 S
b100 Z
b11 '
0#
#361000
b1000 4
b1000 \
#380000
0)
b1000 ?
b1000 F
b1000 U
#420000
1#
#440000
b1010 7
b1010 I
b1010 !
b1010 <
b1010 W
#480000
b10000 A
b10000 C
b10000 ;
b10000 O
b10000 [
b0x0x1 ,
b0x0x1 K
b10000010000001111101011 :
b10000010000001111101011 M
b1011 2
b1011 L
b11111000010000010000001111101011 9
b11111000010000010000001111101011 T
b1000 "
b1000 B
b1000 S
b1000 Z
b100 '
0#
#481000
b1100 4
b1100 \
#500000
b10000 ?
b10000 F
b10000 U
#540000
1#
#560000
b101 7
b101 I
b101 !
b101 <
b101 W
#600000
b11000 A
b11000 C
b11000 ;
b11000 O
b11000 [
b0xx0x ,
b0xx0x K
b10000011000001111101100 :
b10000011000001111101100 M
b1100 2
b1100 L
b11111000010000011000001111101100 9
b11111000010000011000001111101100 T
b1100 "
b1100 B
b1100 S
b1100 Z
b101 '
0#
#601000
b10000 4
b10000 \
#620000
b11000 ?
b11000 F
b11000 U
#660000
1#
#680000
b111111111011111010100111110111101010110110111110111011111111 7
b111111111011111010100111110111101010110110111110111011111111 I
b111111111011111010100111110111101010110110111110111011111111 !
b111111111011111010100111110111101010110110111110111011111111 <
b111111111011111010100111110111101010110110111110111011111111 W
#720000
b100000 A
b100000 C
b100000 ;
b100000 O
b100000 [
b0xxxx ,
b0xxxx K
b10000100000001111101101 :
b10000100000001111101101 M
b1101 2
b1101 L
b11111000010000100000001111101101 9
b11111000010000100000001111101101 T
b10000 "
b10000 B
b10000 S
b10000 Z
b110 '
0#
#721000
b10100 4
b10100 \
#740000
b100000 ?
b100000 F
b100000 U
#780000
1#
#800000
b0 7
b0 I
b0 !
b0 <
b0 W
#840000
b100000 7
b100000 I
bx A
bx C
b10110000 ;
b10110000 O
b10110000 [
bx +
bx N
bx R
b1 @
b1 E
b1 Q
06
08
0>
01
b1011 ,
b1011 K
b10000010110000000101001010 :
b10000010110000000101001010 M
b10101010000 3
b10101010000 P
b1010 -
b1010 J
b1010 2
b1010 L
b10101010000010110000000101001010 9
b10101010000010110000000101001010 T
b10100 "
b10100 B
b10100 S
b10100 Z
b111 '
0#
#841000
b11000 4
b11000 \
#842000
b101 A
b101 C
b101 /
b101 H
b101 V
b1010 0
b1010 D
b1010 G
#860000
x)
bx 7
bx I
bx ?
bx F
bx U
#862000
0)
b1111 7
b1111 I
b1111 ?
b1111 F
b1111 U
#900000
1#
#960000
b0 @
b0 E
b0 Q
b1010 ,
b1010 K
b10000010100000000110001100 :
b10000010100000000110001100 M
b10001010000 3
b10001010000 P
b1100 -
b1100 J
b1100 2
b1100 L
b10001010000010100000000110001100 9
b10001010000010100000000110001100 T
b11000 "
b11000 B
b11000 S
b11000 Z
b1000 '
0#
#961000
b11100 4
b11100 \
#962000
b1010 A
b1010 C
b1010 /
b1010 H
b1010 V
b111111111011111010100111110111101010110110111110111011111111 0
b111111111011111010100111110111101010110110111110111011111111 D
b111111111011111010100111110111101010110110111110111011111111 G
#965000
b1111 A
b1111 C
b1111 /
b1111 H
b1111 V
#980000
1)
b0 7
b0 I
b0 ?
b0 F
b0 U
#982000
0)
b1010 7
b1010 I
b1010 ?
b1010 F
b1010 U
#985000
b1111 7
b1111 I
b1111 ?
b1111 F
b1111 U
#1020000
1#
#1080000
b100 ;
b100 O
b100 [
b0xxxx 7
b0xxxx I
b11 +
b11 N
b11 R
b111 @
b111 E
b111 Q
1=
0.
x8
11
b1100 ,
b1100 K
b10001100 :
b10001100 M
b10110100000 3
b10110100000 P
b100 -
b100 J
b10110100000000000000000010001100 9
b10110100000000000000000010001100 T
b11100 "
b11100 B
b11100 S
b11100 Z
b1001 '
0#
#1081000
b100000 4
b100000 \
#1082000
b111111111011111010100111110111101010110110111110111011111111 A
b111111111011111010100111110111101010110110111110111011111111 C
b111111111011111010100111110111101010110110111110111011111111 /
b111111111011111010100111110111101010110110111110111011111111 H
b111111111011111010100111110111101010110110111110111011111111 V
bx 0
bx D
bx G
#1085000
b1111 A
b1111 C
b1111 /
b1111 H
b1111 V
